hashmerge.py
hashmerge-0.2.dist-info/LICENSE
hashmerge-0.2.dist-info/METADATA
hashmerge-0.2.dist-info/WHEEL
hashmerge-0.2.dist-info/top_level.txt
hashmerge-0.2.dist-info/RECORD
