Metadata-Version: 2.1
Name: hashmerge
Version: 0.2
Summary: Merges two arbitrarily deep hashes into a single hash.
Home-page: https://github.com/lebauce/hashmerge
Author: Sylvain Baubeau
Author-email: bob@glumol.com
License: MIT
Platform: UNKNOWN
Classifier: Development Status :: 4 - Beta
Classifier: Intended Audience :: Developers
Classifier: License :: OSI Approved :: MIT License
Classifier: Operating System :: Unix
Classifier: Programming Language :: Python
Classifier: Topic :: Software Development :: Libraries
